dfttopif/__init__.py
dfttopif/web.py
dfttopif/parsers/__init__.py
dfttopif/parsers/abinit.py
dfttopif/parsers/base.py
dfttopif/parsers/pwscf.py
dfttopif/parsers/vasp.py
dfttopif-0.1.1.dist-info/DESCRIPTION.rst
dfttopif-0.1.1.dist-info/METADATA
dfttopif-0.1.1.dist-info/RECORD
dfttopif-0.1.1.dist-info/WHEEL
dfttopif-0.1.1.dist-info/metadata.json
dfttopif-0.1.1.dist-info/top_level.txt
tests/parsers/__init__.py
tests/parsers/test_pwscf.py
tests/parsers/test_vasp.py
