Metadata-Version: 2.0
Name: dfttopif
Version: 0.1.1
Summary: Library for parsing Density Functional Theory calculations
Home-page: https://github.com/CitrineInformatics/pif-dft
Author: UNKNOWN
Author-email: UNKNOWN
License: 
Requires-Dist: ase
Requires-Dist: pypif
